gerrit_coverage/__init__.py
gerrit_coverage/__main__.py
gerrit_coverage/condense.py
gerrit_coverage/gerrit_coverage.py
gerrit_coverage-0.0.5.dist-info/LICENSE
gerrit_coverage-0.0.5.dist-info/METADATA
gerrit_coverage-0.0.5.dist-info/WHEEL
gerrit_coverage-0.0.5.dist-info/entry_points.txt
gerrit_coverage-0.0.5.dist-info/top_level.txt
gerrit_coverage-0.0.5.dist-info/RECORD
